lpkit/__init__.py
lpkit/core/__init__.py
lpkit/core/model.py
lpkit/graphic/__init__.py
lpkit/graphic/parser.py
lpkit/graphic/plotter.py
lpkit/graphic/solver.py
lpkit/simplex/__init__.py
lpkit/simplex/analysis.py
lpkit/simplex/solver.py
lpkit/simplex/utils.py
lpkit-0.1.4.dist-info/licenses/LICENSE
lpkit-0.1.4.dist-info/METADATA
lpkit-0.1.4.dist-info/WHEEL
lpkit-0.1.4.dist-info/top_level.txt
lpkit-0.1.4.dist-info/RECORD
