Metadata-Version: 2.4
Name: lpkit
Version: 0.1.4
Summary: Ferramentas para visualização e resolução de modelos de Programação Linear.
Home-page: https://github.com/pedroeckel/lpkit
Author: Pedro Eckel
Author-email: pedroeckel@ufpr.br
Classifier: Programming Language :: Python :: 3
Classifier: License :: OSI Approved :: MIT License
Classifier: Operating System :: OS Independent
Requires-Python: >=3.7
License-File: LICENSE
Requires-Dist: sympy
Requires-Dist: matplotlib
Requires-Dist: numpy
Requires-Dist: pandas
Dynamic: author
Dynamic: author-email
Dynamic: classifier
Dynamic: home-page
Dynamic: license-file
Dynamic: requires-dist
Dynamic: requires-python
Dynamic: summary
